bmemcached/__init__.py
bmemcached/compat.py
bmemcached/exceptions.py
bmemcached/protocol.py
bmemcached/utils.py
bmemcached/client/__init__.py
bmemcached/client/constants.py
bmemcached/client/distributed.py
bmemcached/client/mixin.py
bmemcached/client/replicating.py
python_binary_memcached-0.31.3.dist-info/LICENSE
python_binary_memcached-0.31.3.dist-info/METADATA
python_binary_memcached-0.31.3.dist-info/WHEEL
python_binary_memcached-0.31.3.dist-info/top_level.txt
python_binary_memcached-0.31.3.dist-info/RECORD
