Metadata-Version: 2.1
Name: python-binary-memcached
Version: 0.31.3
Summary: A pure python module to access memcached via its binary protocol with SASL auth support
Home-page: https://github.com/jaysonsantos/python-binary-memcached
Author: Jayson Reis
Author-email: santosdosreis@gmail.com
Classifier: Development Status :: 4 - Beta
Classifier: License :: OSI Approved :: MIT License
Classifier: Operating System :: OS Independent
Classifier: Programming Language :: Python :: 2.7
Classifier: Programming Language :: Python :: 3.4
Classifier: Programming Language :: Python :: 3.5
Classifier: Programming Language :: Python :: 3.6
Classifier: Programming Language :: Python :: 3.7
Classifier: Programming Language :: Python :: 3.8
Classifier: Programming Language :: Python :: 3.9
License-File: LICENSE
Requires-Dist: six
Requires-Dist: uhashring
